LICENSE
README.md
database_logger.py
datamap.py
mqtt_logger.py
plotlytest.py
remeha.py
remeha_convert.py
remeha_core.py
remeha_info.py
setup.py
config/translations.json
remeha_tz.egg-info/PKG-INFO
remeha_tz.egg-info/SOURCES.txt
remeha_tz.egg-info/dependency_links.txt
remeha_tz.egg-info/requires.txt
remeha_tz.egg-info/top_level.txt