Metadata-Version: 2.1
Name: remeha-tz
Version: 0.12
Summary: UNKNOWN
Home-page: https://github.com/TheRikke/remeha_tz
Author: rikky
Author-email: rikky@web.de
License: UNKNOWN
Platform: UNKNOWN
Requires-Python: >=3.6
License-File: LICENSE
